yaes.py
yaes-0.2.5.dist-info/LICENSE.txt
yaes-0.2.5.dist-info/METADATA
yaes-0.2.5.dist-info/WHEEL
yaes-0.2.5.dist-info/top_level.txt
yaes-0.2.5.dist-info/RECORD
