Metadata-Version: 2.1
Name: yaes
Version: 0.2.5
Summary: Yet Another Expansion Syntax (pronounced 'Yasssss Kweeeeen')
Home-page: https://yaes.readthedocs.io/en/0.2.5/
Download-URL: https://github.com/gaf3/yaes
Author: Gaffer Fitch
Author-email: yaes@gaf3.com
Classifier: Programming Language :: Python :: 3
Classifier: License :: OSI Approved :: MIT License
License-File: LICENSE.txt
Requires-Dist: Jinja2==3.1.2
Requires-Dist: overscore==0.1.2
Requires-Dist: MarkupSafe==2.1.5
